<?xml version="1.0" encoding="UTF-8" standalone="yes"?>
<KeyValueMapOperations async="false" continueOnError="false" enabled="true" name="SoF_KV_ReadClientSecret" mapIdentifier="SoF_Secrets">
    <DisplayName>SoF_KV_ReadClientSecret</DisplayName>
    <Properties/>
    <ExclusiveCache>false</ExclusiveCache>
    <ExpiryTimeInSecs>300</ExpiryTimeInSecs>
    <InitialEntries/>
    <Get assignTo="private.FHIR_ISSUER_CLIENT_SECRET">
        <Key>
            <Parameter ref="FHIR_ISSUER_CLIENT_SECRET"/>
        </Key>
    </Get>
    <Scope>environment</Scope>
</KeyValueMapOperations>